noise2sim/__init__.py
noise2sim/version.py
noise2sim/config/__init__.py
noise2sim/config/config.py
noise2sim/data/__init__.py
noise2sim/data/bulid_data.py
noise2sim/data/datasets/__init__.py
noise2sim/data/datasets/bsd_npy.py
noise2sim/data/datasets/data_ldct.py
noise2sim/data/datasets/data_lmdb.py
noise2sim/data/datasets/data_pcct.py
noise2sim/data/datasets/ldct_npy.py
noise2sim/modeling/__init__.py
noise2sim/modeling/architectures/__init__.py
noise2sim/modeling/architectures/build_architecture.py
noise2sim/modeling/architectures/common_denoiser.py
noise2sim/modeling/denoiser_head/__init__.py
noise2sim/modeling/denoiser_head/build_denoiser_head.py
noise2sim/modeling/denoiser_head/denoiser_head.py
noise2sim/modeling/networks/__init__.py
noise2sim/modeling/networks/build_base_module.py
noise2sim/modeling/networks/unet.py
noise2sim/solver/__init__.py
noise2sim/solver/build.py
noise2sim/solver/lr_scheduler.py
noise2sim/tools/__init__.py
noise2sim/tools/nearest_search.py
noise2sim/tools/prepare_bsd400_lmdb.py
noise2sim/tools/prepare_ldct.py
noise2sim/tools/test_ldct.py
noise2sim/tools/test_pcct.py
noise2sim/tools/train.py
noise2sim/utils/__init__.py
noise2sim/utils/c2_model_loading.py
noise2sim/utils/checkpoint.py
noise2sim/utils/collect_env.py
noise2sim/utils/comm.py
noise2sim/utils/env.py
noise2sim/utils/evaluation.py
noise2sim/utils/imports.py
noise2sim/utils/logger.py
noise2sim/utils/metric_logger.py
noise2sim/utils/misc.py
noise2sim/utils/miscellaneous.py
noise2sim/utils/model_serialization.py
noise2sim/utils/model_zoo.py
noise2sim/utils/path.py
noise2sim/utils/registry.py
noise2sim/utils/visualization.py
noise2sim-0.1.2.data/scripts/train.py
noise2sim-0.1.2.dist-info/METADATA
noise2sim-0.1.2.dist-info/WHEEL
noise2sim-0.1.2.dist-info/top_level.txt
noise2sim-0.1.2.dist-info/RECORD
