Metadata-Version: 2.1
Name: noise2sim
Version: 0.1.2
Summary: Noise2Sim suppresses both independent and correlated nosies through training a neural networkin a self-supervised learning manner.
Home-page: https://github.com/niuchuangnn/noise2sim
Author: Chuang Niu
Author-email: niuchuangnn@gmail.com
License: BSD 3-Clause License
Project-URL: Repository, https://github.com/niuchuangnn/noise2sim
Platform: UNKNOWN
Classifier: Development Status :: 4 - Beta
Classifier: Intended Audience :: Science/Research
Classifier: Topic :: Scientific/Engineering
Classifier: License :: OSI Approved :: BSD License
Classifier: Programming Language :: Python :: 3.6
Requires-Dist: lmdb
Requires-Dist: tqdm
Requires-Dist: imageio
Requires-Dist: addict
Requires-Dist: opencv-python
Requires-Dist: matplotlib
Requires-Dist: pydicom
Requires-Dist: scipy
Requires-Dist: faiss-gpu
Requires-Dist: scikit-image
